macrodatabase/__init__.py
macrodatabase/collect_data.py
macrodatabase/json_curated.py
macrodatabase/json_database.py
macrodatabase-1.0.3.dist-info/LICENSE
macrodatabase-1.0.3.dist-info/METADATA
macrodatabase-1.0.3.dist-info/WHEEL
macrodatabase-1.0.3.dist-info/top_level.txt
macrodatabase-1.0.3.dist-info/RECORD
