Metadata-Version: 2.1
Name: macrodatabase
Version: 1.0.3
Summary: This is a macro database of 570.000+ data series containing International Data (150+ countries), Interest Rates, Inflation, Monetary Data, U.S. (regional) data, Commodities, Real Estate and so much more. U.S. States and Countries curation is also included.
Home-page: https://github.com/OpenBB-finance/MacroDatabase
Author: OpenBB
Author-email: hello@openbb.co
License: MIT
Keywords: macroeconomics,database,fred
Platform: UNKNOWN
Classifier: Development Status :: 5 - Production/Stable
Classifier: Intended Audience :: Financial and Insurance Industry
Classifier: Topic :: Office/Business :: Financial :: Investment
Classifier: License :: OSI Approved :: MIT License
Classifier: Operating System :: OS Independent
Classifier: Programming Language :: Python :: 3
License-File: LICENSE
